BMI_APP/__init__.py
BMI_APP/myhealth.py
BMI_APP-0.2.dist-info/LICENSE
BMI_APP-0.2.dist-info/METADATA
BMI_APP-0.2.dist-info/WHEEL
BMI_APP-0.2.dist-info/top_level.txt
BMI_APP-0.2.dist-info/RECORD
