Metadata-Version: 2.1
Name: BMI-APP
Version: 0.2
Summary: BMI, BMI Category, Health Risk calculation
Home-page: https://github.com/manishgupta-ind/code-20220528-manishgupta
Author: Manish Gupta
Author-email: mgupta.power@gmail.com
License: MIT
Requires-Python: >=3.6
License-File: LICENSE
Requires-Dist: BMI-APP
